{
	"name": "DataLakeDataset",
	"properties": {
		"linkedServiceName": {
			"referenceName": "DataLakeLinkedService",
			"type": "LinkedServiceReference"
		},
		"parameters": {
			"sinkFolderName": {
				"type": "String"
			},
			"sinkFileName": {
				"type": "String"
			}
		},
		"annotations": [],
		"type": "DelimitedText",
		"typeProperties": {
			"location": {
				"type": "AzureBlobFSLocation",
				"fileName": {
					"value": "@dataset().sinkFileName",
					"type": "Expression"
				},
				"folderPath": {
					"value": "@dataset().sinkFolderName",
					"type": "Expression"
				},
				"fileSystem": "bronze"
			},
			"columnDelimiter": ",",
			"escapeChar": "\\",
			"firstRowAsHeader": true,
			"quoteChar": "\""
		},
		"schema": []
	},
	"type": "Microsoft.DataFactory/factories/datasets"
}